Workbook

Sheet Top 5 Research Priorities
A1: Rank | B1: Company | C1: Segment | D1: Score / 5 | E1: Hiring evidence | F1: Complexity | G1: Product relevance* | H1: Research accessibility* | I1: Official source URL | J1: Next research action
A2: 1 | B2: =INDEX('Priority Model'!$B$2:$B$21,MATCH($A2,'Priority Model'!$I$2:$I$21,0)) | C2: =INDEX('Priority Model'!$C$2:$C$21,MATCH($A2,'Priority Model'!$I$2:$I$21,0)) | D2: =INDEX('Priority Model'!$H$2:$H$21,MATCH($A2,'Priority Model'!$I$2:$I$21,0)) | E2: =INDEX('Priority Model'!$D$2:$D$21,MATCH($A2,'Priority Model'!$I$2:$I$21,0)) | F2: =INDEX('Priority Model'!$E$2:$E$21,MATCH($A2,'Priority Model'!$I$2:$I$21,0)) | G2: =INDEX('Priority Model'!$F$2:$F$21,MATCH($A2,'Priority Model'!$I$2:$I$21,0)) | H2: =INDEX('Priority Model'!$G$2:$G$21,MATCH($A2,'Priority Model'!$I$2:$I$21,0)) | I2: =INDEX('Priority Model'!$L$2:$L$21,MATCH($A2,'Priority Model'!$I$2:$I$21,0)) | J2: =INDEX('Priority Model'!$M$2:$M$21,MATCH($A2,'Priority Model'!$I$2:$I$21,0))
A3: 2 | B3: =INDEX('Priority Model'!$B$2:$B$21,MATCH($A3,'Priority Model'!$I$2:$I$21,0)) | C3: =INDEX('Priority Model'!$C$2:$C$21,MATCH($A3,'Priority Model'!$I$2:$I$21,0)) | D3: =INDEX('Priority Model'!$H$2:$H$21,MATCH($A3,'Priority Model'!$I$2:$I$21,0)) | E3: =INDEX('Priority Model'!$D$2:$D$21,MATCH($A3,'Priority Model'!$I$2:$I$21,0)) | F3: =INDEX('Priority Model'!$E$2:$E$21,MATCH($A3,'Priority Model'!$I$2:$I$21,0)) | G3: =INDEX('Priority Model'!$F$2:$F$21,MATCH($A3,'Priority Model'!$I$2:$I$21,0)) | H3: =INDEX('Priority Model'!$G$2:$G$21,MATCH($A3,'Priority Model'!$I$2:$I$21,0)) | I3: =INDEX('Priority Model'!$L$2:$L$21,MATCH($A3,'Priority Model'!$I$2:$I$21,0)) | J3: =INDEX('Priority Model'!$M$2:$M$21,MATCH($A3,'Priority Model'!$I$2:$I$21,0))
A4: 3 | B4: =INDEX('Priority Model'!$B$2:$B$21,MATCH($A4,'Priority Model'!$I$2:$I$21,0)) | C4: =INDEX('Priority Model'!$C$2:$C$21,MATCH($A4,'Priority Model'!$I$2:$I$21,0)) | D4: =INDEX('Priority Model'!$H$2:$H$21,MATCH($A4,'Priority Model'!$I$2:$I$21,0)) | E4: =INDEX('Priority Model'!$D$2:$D$21,MATCH($A4,'Priority Model'!$I$2:$I$21,0)) | F4: =INDEX('Priority Model'!$E$2:$E$21,MATCH($A4,'Priority Model'!$I$2:$I$21,0)) | G4: =INDEX('Priority Model'!$F$2:$F$21,MATCH($A4,'Priority Model'!$I$2:$I$21,0)) | H4: =INDEX('Priority Model'!$G$2:$G$21,MATCH($A4,'Priority Model'!$I$2:$I$21,0)) | I4: =INDEX('Priority Model'!$L$2:$L$21,MATCH($A4,'Priority Model'!$I$2:$I$21,0)) | J4: =INDEX('Priority Model'!$M$2:$M$21,MATCH($A4,'Priority Model'!$I$2:$I$21,0))
A5: 4 | B5: =INDEX('Priority Model'!$B$2:$B$21,MATCH($A5,'Priority Model'!$I$2:$I$21,0)) | C5: =INDEX('Priority Model'!$C$2:$C$21,MATCH($A5,'Priority Model'!$I$2:$I$21,0)) | D5: =INDEX('Priority Model'!$H$2:$H$21,MATCH($A5,'Priority Model'!$I$2:$I$21,0)) | E5: =INDEX('Priority Model'!$D$2:$D$21,MATCH($A5,'Priority Model'!$I$2:$I$21,0)) | F5: =INDEX('Priority Model'!$E$2:$E$21,MATCH($A5,'Priority Model'!$I$2:$I$21,0)) | G5: =INDEX('Priority Model'!$F$2:$F$21,MATCH($A5,'Priority Model'!$I$2:$I$21,0)) | H5: =INDEX('Priority Model'!$G$2:$G$21,MATCH($A5,'Priority Model'!$I$2:$I$21,0)) | I5: =INDEX('Priority Model'!$L$2:$L$21,MATCH($A5,'Priority Model'!$I$2:$I$21,0)) | J5: =INDEX('Priority Model'!$M$2:$M$21,MATCH($A5,'Priority Model'!$I$2:$I$21,0))
A6: 5 | B6: =INDEX('Priority Model'!$B$2:$B$21,MATCH($A6,'Priority Model'!$I$2:$I$21,0)) | C6: =INDEX('Priority Model'!$C$2:$C$21,MATCH($A6,'Priority Model'!$I$2:$I$21,0)) | D6: =INDEX('Priority Model'!$H$2:$H$21,MATCH($A6,'Priority Model'!$I$2:$I$21,0)) | E6: =INDEX('Priority Model'!$D$2:$D$21,MATCH($A6,'Priority Model'!$I$2:$I$21,0)) | F6: =INDEX('Priority Model'!$E$2:$E$21,MATCH($A6,'Priority Model'!$I$2:$I$21,0)) | G6: =INDEX('Priority Model'!$F$2:$F$21,MATCH($A6,'Priority Model'!$I$2:$I$21,0)) | H6: =INDEX('Priority Model'!$G$2:$G$21,MATCH($A6,'Priority Model'!$I$2:$I$21,0)) | I6: =INDEX('Priority Model'!$L$2:$L$21,MATCH($A6,'Priority Model'!$I$2:$I$21,0)) | J6: =INDEX('Priority Model'!$M$2:$M$21,MATCH($A6,'Priority Model'!$I$2:$I$21,0))
A9: * Product relevance and research accessibility are analyst assessments, not independently verified facts.
A10: These are research priorities only. No outreach, buyer intent, budget, or deal qualification is implied.

Sheet Account Research
A1: ID | B1: Company | C1: Segment | D1: Geographic relevance | E1: Verified public signal (fact) | F1: Exact official source URL | G1: Evidence strength | H1: Evidence checked (date) | I1: Verification use case (hypothesis) | J1: Buyer persona (hypothesis; role only) | K1: Vendor / budget / purchase intent | L1: Next research action | M1: Research status | N1: Notes / corrections
A2: 1 | B2: Infosys | C2: IT services | D2: India | E2: India job portal lists multiple technology and consulting roles in Bengaluru, Hyderabad and Pune. | F2: https://career.infosys.com/joblist | G2: Specific India vacancies | H2: 46318 | I2: Multi-location verification coordination | J2: Head of Talent Acquisition | K2: Unknown; not verified | L2: Check hiring channels and whether verification is centralized. | M2: Desk research only
A3: 2 | B3: TCS | C3: IT services | D3: India | E3: India careers page offers entry-level and lateral recruitment; lists background-check agency partner access. | F3: https://www.tcs.com/careers/india | G3: Recruitment process / agency access | H3: 46318 | I3: Coordination across graduate and lateral verification; mature incumbent process likely | J3: Head of HR Operations | K3: Unknown; not verified | L3: Research whether vendor access indicates an established screening ecosystem. | M3: Desk research only
A4: 3 | B4: Wipro | C4: IT services | D4: India | E4: Official Wipro job posting lists HR Business Partner role in Bengaluru dated 16 Oct 2026. | F4: https://careers.wipro.com/job/Bengaluru-HR-Business-Partner-IND-560035/210624-en_US/ | G4: Dated India vacancy | H4: 46318 | I4: Consistent onboarding controls across teams | J4: HR Operations Director | K4: Unknown; not verified | L4: Find additional current roles and screening policy. | M4: Desk research only
A5: 4 | B5: HCLTech | C5: IT services | D5: India | E5: Official India careers portal publishes India openings and job alerts. | F5: https://careers.hcltech.com/go/India/9553955/ | G5: India recruitment portal | H5: 46318 | I5: Graduate and lateral screening workflow | J5: Talent Acquisition Operations Lead | K5: Unknown; not verified | L5: Find individual dated India vacancies. | M5: Desk research only
A6: 5 | B6: Tech Mahindra | C6: IT services | D6: India | E6: Official job portal lists Bengaluru engineering, Hyderabad network, Kolkata data science and Mumbai cybersecurity roles. | F6: https://careers.techmahindra.com/ | G6: Specific India vacancies | H6: 46318 | I6: Multi-city hiring verification visibility | J6: Head of Recruitment Operations | K6: Unknown; not verified | L6: Review hiring divisions and existing screening workflow. | M6: Desk research only
A7: 6 | B7: Coforge | C7: IT services | D7: India | E7: Official portal lists 107 India openings and cities including Greater Noida, Bengaluru, Hyderabad, Chennai (changing snapshot). | F7: https://careers.coforge.com/coforge/ | G7: India vacancies + portal count | H7: 46318 | I7: Centralized status tracking for multiple hiring sites | J7: Head of Talent Acquisition | K7: Unknown; not verified | L7: Refresh India job count; investigate BPS versus IT hiring. | M7: Desk research only
A8: 7 | B8: Persistent Systems | C8: Digital engineering | D8: India | E8: Official job posting describes Senior Network Security Engineer in Noida. | F8: https://careers.persistent.com/jobview/dev-lead-india-noida-2026100716131920 | G8: Specific India vacancy | H8: 46318 | I8: Screening specialist technical hires | J8: Talent Acquisition Lead | K8: Unknown; not verified | L8: Find hiring volume indicators and screening ownership. | M8: Desk research only
A9: 8 | B9: Birlasoft | C9: IT services | D9: India | E9: Official India openings portal lists 22 Oct 2026 vacancies in Hyderabad, Pune, Noida and Bengaluru. | F9: https://jobs.birlasoft.com/go/India/684744/ | G9: Dated multi-city vacancies | H9: 46318 | I9: Consistent employee screening across delivery centers | J9: Head of HR Operations | K9: Unknown; not verified | L9: Confirm current postings and relevant HR decision function. | M9: Desk research only
A10: 9 | B10: Zensar Technologies | C10: IT services | D10: India | E10: Official careers site offers India/APAC opportunity search and describes global teams including Pune. | F10: https://www.zensar.com/careers | G10: Recruitment portal only | H10: 46318 | I10: Structured verification for multi-location recruiting | J10: Head of Talent Acquisition | K10: Unknown; not verified | L10: Identify a specific India opening before personalization. | M10: Desk research only
A11: 10 | B11: Zoho | C11: SaaS | D11: India | E11: Official careers page offers open roles and candidate portal; lists Chennai and Tenkasi offices. | F11: https://www.zoho.com/careers/ | G11: Recruitment portal only | H11: 46318 | I11: Verification across engineering and sales hiring | J11: Talent Acquisition Head | K11: Unknown; not verified | L11: Confirm India vacancies and whether screening is in-house. | M11: Desk research only
A12: 11 | B12: Postman | C12: SaaS | D12: India | E12: Official portal lists Bangalore engineering and sales compensation roles; 29 global open positions at snapshot. | F12: https://www.postman.com/company/careers/open-positions/ | G12: Specific India vacancies | H12: 46318 | I12: Cross-functional onboarding verification | J12: People Operations Lead | K12: Unknown; not verified | L12: Verify Bangalore roles remain open; research procurement. | M12: Desk research only
A13: 12 | B13: CleverTap | C13: SaaS | D13: India | E13: Official careers page reports 550+ employees and lists openings in Bangalore and Gurgaon. | F13: https://clevertap.com/careers/ | G13: India vacancies + workforce claim | H13: 46318 | I13: Consistent screening across offices and functions | J13: Head of People Operations | K13: Unknown; not verified | L13: Review India roles and existing HR tools. | M13: Desk research only
... A21: 20 | B21: BrowserStack | C21: SaaS | D21: India | E21: Official Workday listing advertises Business Development Representative, India Remote. | F21: https://browserstack.wd3.myworkdayjobs.com/en-US/External/job/Sales-Development-Representative_JR103474 | G21: Specific India vacancy | H21: 46318 | I21: Verification for remote and distributed hiring | J21: Head of Talent Acquisition | K21: Unknown; not verified | L21: Confirm listing still active and how remote hiring is screened. | M21: Desk research only

Sheet Method & Definitions
A1: RECRIAUTH | INDEPENDENT GTM RESEARCH
A2: Scope | B2: 20 real IT services / SaaS organizations with India-related hiring or workforce evidence.
A3: As-of date | B3: 23 October 2026. Job portals are dynamic; snapshot counts may change.
A4: Affiliation | B4: Independent educational portfolio exercise; not affiliated with Recrivio or the listed companies.
A5: Verified facts | B5: Only statements supported by the exact official URL in each account row.
A6: Evidence strength | B6: Dated India vacancy > specific India vacancy > recruitment program/portal > workforce-only signal. Not a purchase-intent score.
A7: Hypotheses | B7: Potential verification use cases and buyer roles are reasoned possibilities, not claims of existing needs or actual contacts.
A8: Unknowns | B8: No verified vendor, budget, procurement timing, decision maker, buying intent, relationship or deal size.
A9: No outreach performed | B9: Research status is desk research only; no emails sent, meetings booked or sales generated.
A10: Prioritization | B10: Step 4 will score accounts transparently; no commercial score assigned in this workbook.
A11: Research practice | B11: Before outbound, revisit URLs, confirm a current hiring signal, validate fit, and check vendor conflicts and privacy/compliance.
A12: Color key | B12: Green = imported source fact; orange = hypothesis/unknown; blue = editable follow-up; gray = static context.
A13: Evidence caveat | B13: A general careers page or hiring process does not prove an active India vacancy. Some sources are weaker than others.
A14: Privacy | B14: Buyer personas are role categories only; no individual names, personal emails, or contact details collected.

Sheet Priority Model
A1: ID | B1: Company | C1: Segment | D1: Hiring evidence (1-5) | E1: Complexity (1-5) | F1: Product relevance (1-5; hypothesis) | G1: Research accessibility (1-5) | H1: Weighted score / 5 | I1: Rank | J1: Evidence / rationale | K1: Assumption / uncertainty | L1: Official source URL | M1: Next research action
A2: 1 | B2: Infosys | C2: IT services | D2: 4 | E2: 5 | F2: 4 | G2: 4 | H2: =SUMPRODUCT(D2:G2,'Scoring Guide'!$B$2:$B$5) | I2: =RANK.EQ(H2,$H$2:$H$21,0)+COUNTIF($H$2:H2,H2)-1 | J2: India job portal lists multiple technology and consulting roles in Bengaluru, Hyderabad and Pune. | K2: Product relevance and research accessibility are analyst hypotheses; vendor, budget and buyer intent unknown. Unknown; not verified | L2: https://career.infosys.com/joblist | M2: Check hiring channels and whether verification is centralized.
A3: 2 | B3: TCS | C3: IT services | D3: 3 | E3: 5 | F3: 3 | G3: 4 | H3: =SUMPRODUCT(D3:G3,'Scoring Guide'!$B$2:$B$5) | I3: =RANK.EQ(H3,$H$2:$H$21,0)+COUNTIF($H$2:H3,H3)-1 | J3: India careers page offers entry-level and lateral recruitment; lists background-check agency partner access. | K3: Product relevance and research accessibility are analyst hypotheses; vendor, budget and buyer intent unknown. Unknown; not verified | L3: https://www.tcs.com/careers/india | M3: Research whether vendor access indicates an established screening ecosystem.
A4: 3 | B4: Wipro | C4: IT services | D4: 5 | E4: 3 | F4: 3 | G4: 4 | H4: =SUMPRODUCT(D4:G4,'Scoring Guide'!$B$2:$B$5) | I4: =RANK.EQ(H4,$H$2:$H$21,0)+COUNTIF($H$2:H4,H4)-1 | J4: Official Wipro job posting lists HR Business Partner role in Bengaluru dated 16 Oct 2026. | K4: Product relevance and research accessibility are analyst hypotheses; vendor, budget and buyer intent unknown. Unknown; not verified | L4: https://careers.wipro.com/job/Bengaluru-HR-Business-Partner-IND-560035/210624-en_US/ | M4: Find additional current roles and screening policy.
A5: 4 | B5: HCLTech | C5: IT services | D5: 3 | E5: 4 | F5: 4 | G5: 3 | H5: =SUMPRODUCT(D5:G5,'Scoring Guide'!$B$2:$B$5) | I5: =RANK.EQ(H5,$H$2:$H$21,0)+COUNTIF($H$2:H5,H5)-1 | J5: Official India careers portal publishes India openings and job alerts. | K5: Product relevance and research accessibility are analyst hypotheses; vendor, budget and buyer intent unknown. Unknown; not verified | L5: https://careers.hcltech.com/go/India/9553955/ | M5: Find individual dated India vacancies.
A6: 5 | B6: Tech Mahindra | C6: IT services | D6: 4 | E6: 4 | F6: 4 | G6: 4 | H6: =SUMPRODUCT(D6:G6,'Scoring Guide'!$B$2:$B$5) | I6: =RANK.EQ(H6,$H$2:$H$21,0)+COUNTIF($H$2:H6,H6)-1 | J6: Official job portal lists Bengaluru engineering, Hyderabad network, Kolkata data science and Mumbai cybersecurity roles. | K6: Product relevance and research accessibility are analyst hypotheses; vendor, budget and buyer intent unknown. Unknown; not verified | L6: https://careers.techmahindra.com/ | M6: Review hiring divisions and existing screening workflow.
A7: 6 | B7: Coforge | C7: IT services | D7: 5 | E7: 5 | F7: 4 | G7: 5 | H7: =SUMPRODUCT(D7:G7,'Scoring Guide'!$B$2:$B$5) | I7: =RANK.EQ(H7,$H$2:$H$21,0)+COUNTIF($H$2:H7,H7)-1 | J7: Official portal lists 107 India openings and cities including Greater Noida, Bengaluru, Hyderabad, Chennai (changing snapshot). | K7: Product relevance and research accessibility are analyst hypotheses; vendor, budget and buyer intent unknown. Unknown; not verified | L7: https://careers.coforge.com/coforge/ | M7: Refresh India job count; investigate BPS versus IT hiring.
A8: 7 | B8: Persistent Systems | C8: Digital engineering | D8: 4 | E8: 3 | F8: 3 | G8: 4 | H8: =SUMPRODUCT(D8:G8,'Scoring Guide'!$B$2:$B$5) | I8: =RANK.EQ(H8,$H$2:$H$21,0)+COUNTIF($H$2:H8,H8)-1 | J8: Official job posting describes Senior Network Security Engineer in Noida. | K8: Product relevance and research accessibility are analyst hypotheses; vendor, budget and buyer intent unknown. Unknown; not verified | L8: https://careers.persistent.com/jobview/dev-lead-india-noida-2026100716131920 | M8: Find hiring volume indicators and screening ownership.
A9: 8 | B9: Birlasoft | C9: IT services | D9: 5 | E9: 4 | F9: 4 | G9: 4 | H9: =SUMPRODUCT(D9:G9,'Scoring Guide'!$B$2:$B$5) | I9: =RANK.EQ(H9,$H$2:$H$21,0)+COUNTIF($H$2:H9,H9)-1 | J9: Official India openings portal lists 22 Oct 2026 vacancies in Hyderabad, Pune, Noida and Bengaluru. | K9: Product relevance and research accessibility are analyst hypotheses; vendor, budget and buyer intent unknown. Unknown; not verified | L9: https://jobs.birlasoft.com/go/India/684744/ | M9: Confirm current postings and relevant HR decision function.
A10: 9 | B10: Zensar Technologies | C10: IT services | D10: 3 | E10: 3 | F10: 3 | G10: 3 | H10: =SUMPRODUCT(D10:G10,'Scoring Guide'!$B$2:$B$5) | I10: =RANK.EQ(H10,$H$2:$H$21,0)+COUNTIF($H$2:H10,H10)-1 | J10: Official careers site offers India/APAC opportunity search and describes global teams including Pune. | K10: Product relevance and research accessibility are analyst hypotheses; vendor, budget and buyer intent unknown. Unknown; not verified | L10: https://www.zensar.com/careers | M10: Identify a specific India opening before personalization.
A11: 10 | B11: Zoho | C11: SaaS | D11: 3 | E11: 3 | F11: 3 | G11: 3 | H11: =SUMPRODUCT(D11:G11,'Scoring Guide'!$B$2:$B$5) | I11: =RANK.EQ(H11,$H$2:$H$21,0)+COUNTIF($H$2:H11,H11)-1 | J11: Official careers page offers open roles and candidate portal; lists Chennai and Tenkasi offices. | K11: Product relevance and research accessibility are analyst hypotheses; vendor, budget and buyer intent unknown. Unknown; not verified | L11: https://www.zoho.com/careers/ | M11: Confirm India vacancies and whether screening is in-house.
A12: 11 | B12: Postman | C12: SaaS | D12: 4 | E12: 4 | F12: 4 | G12: 5 | H12: =SUMPRODUCT(D12:G12,'Scoring Guide'!$B$2:$B$5) | I12: =RANK.EQ(H12,$H$2:$H$21,0)+COUNTIF($H$2:H12,H12)-1 | J12: Official portal lists Bangalore engineering and sales compensation roles; 29 global open positions at snapshot. | K12: Product relevance and research accessibility are analyst hypotheses; vendor, budget and buyer intent unknown. Unknown; not verified | L12: https://www.postman.com/company/careers/open-positions/ | M12: Verify Bangalore roles remain open; research procurement.
A13: 12 | B13: CleverTap | C13: SaaS | D13: 5 | E13: 4 | F13: 4 | G13: 5 | H13: =SUMPRODUCT(D13:G13,'Scoring Guide'!$B$2:$B$5) | I13: =RANK.EQ(H13,$H$2:$H$21,0)+COUNTIF($H$2:H13,H13)-1 | J13: Official careers page reports 550+ employees and lists openings in Bangalore and Gurgaon. | K13: Product relevance and research accessibility are analyst hypotheses; vendor, budget and buyer intent unknown. Unknown; not verified | L13: https://clevertap.com/careers/ | M13: Review India roles and existing HR tools.
... A21: 20 | B21: BrowserStack | C21: SaaS | D21: 4 | E21: 3 | F21: 4 | G21: 4 | H21: =SUMPRODUCT(D21:G21,'Scoring Guide'!$B$2:$B$5) | I21: =RANK.EQ(H21,$H$2:$H$21,0)+COUNTIF($H$2:H21,H21)-1 | J21: Official Workday listing advertises Business Development Representative, India Remote. | K21: Product relevance and research accessibility are analyst hypotheses; vendor, budget and buyer intent unknown. Unknown; not verified | L21: https://browserstack.wd3.myworkdayjobs.com/en-US/External/job/Sales-Development-Representative_JR103474 | M21: Confirm listing still active and how remote hiring is screened.

Sheet Scoring Guide
A1: CRITERION | B1: WEIGHT | C1: SCORING RUBRIC / LIMITATION
A2: Hiring evidence strength | B2: 0.4 | C2: 5 = dated/specific India openings; 4 = specific vacancies or portal count; 3 = recruitment portal or channels; 2 = recruitment-process page; 1 = weak/general evidence.
A3: Hiring complexity signals | B3: 0.25 | C3: 5 = documented multi-location AND multiple hiring channels/functions; 4 = multi-location or multi-function; 3 = some location/function breadth; 2 = limited detail; 1 = no details.
A4: Potential product relevance | B4: 0.2 | C4: Analyst hypothesis only: 5 = clear process integration angle; 4 = multi-team screening workflow; 3 = general screening use case; 2 = uncertain; 1 = weak.
A5: Research accessibility | B5: 0.15 | C5: Analyst assessment: 5 = detailed official jobs and roles; 4 = usable jobs/location information; 3 = careers page; 2 = limited detail; 1 = sparse.
A6: IMPORTANT | B6: Scores are research prioritization judgments, NOT vendor-fit validation, buyer intent, sales opportunity, or revenue forecast.
A7: Evidence | B7: Source URLs and original descriptions are retained on Account Research.
A8: Scoring | B8: All four scores are editable analyst inputs. Weight and total formulas recalculate in Excel.
A9: Caution | B9: Higher score may favor information-rich large enterprises; procurement access remains unknown.
